bankatestlib/__init__.py
bankatestlib/math_utils.py
bankatestlib-0.1.0.dist-info/licenses/LICENSE
bankatestlib-0.1.0.dist-info/METADATA
bankatestlib-0.1.0.dist-info/WHEEL
bankatestlib-0.1.0.dist-info/top_level.txt
bankatestlib-0.1.0.dist-info/RECORD
