Metadata-Version: 2.4
Name: bankatestlib
Version: 0.1.0
Summary: A simple test Python library by Piyush Banka.
Author-email: Piyush Banka <your-email@example.com>
License: MIT
Project-URL: Homepage, https://github.com/yourusername/bankatestlib
Requires-Python: >=3.8
License-File: LICENSE
Dynamic: license-file
